dktorecuperedb/__init__.py
dktorecuperedb/__version__.py
dktorecuperedb/bible/__init__.py
dktorecuperedb/bible/_fill_verses.py
dktorecuperedb/bible/_on_a_year.py
dktorecuperedb/bible/_parse_ref.py
dktorecuperedb/bible/_reference_to_text.py
dktorecuperedb/bible/db/__init__.py
dktorecuperedb/bible/db/_get_book_name.py
dktorecuperedb/bible/db/_get_min_max_chapter_number.py
dktorecuperedb/bible/db/_get_min_max_verse_number.py
dktorecuperedb/bible/db/_get_range_verse.py
dktorecuperedb/bible/db/_get_text_one_verse.py
dktorecuperedb/bible/db/request2int.py
dktorecuperedb/bible/db/request2str.py
dktorecuperedb/bible/verse/__init__.py
dktorecuperedb/compendium/__init__.py
dktorecuperedb/compendium/content_compendium/__init__.py
dktorecuperedb/compendium/content_compendium/_collection2data.py
dktorecuperedb/compendium/content_compendium/_fetch_content.py
dktorecuperedb/compendium/content_compendium/_fetch_index.py
dktorecuperedb/compendium/content_compendium/_get_index.py
dktorecuperedb/compendium/content_compendium/_get_whatever_i_can.py
dktorecuperedb/compendium/content_compendium/sort_datas.py
dktorecuperedb/compendium/content_sequence/__init__.py
dktorecuperedb/compendium/db/__init__.py
dktorecuperedb/compendium/db/_get_alternatives.py
dktorecuperedb/compendium/db/_get_collections.py
dktorecuperedb/compendium/db/_get_item_compendium.py
dktorecuperedb/compendium/db/_get_sequence.py
dktorecuperedb/compendium/db/_get_sequence_index.py
dktorecuperedb/compendium/db/_get_sommaire.py
dktorecuperedb/office/__init__.py
dktorecuperedb/office/_check_input.py
dktorecuperedb/office/_get_alternatives.py
dktorecuperedb/office/_get_hunfolding.py
dktorecuperedb/office/_get_info_from_db.py
dktorecuperedb/office/_get_office.py
dktorecuperedb/office/_hunfolding_from_json.py
dktorecuperedb/office/_update_hunfolding.py
dktorecuperedb/office/db/__init__.py
dktorecuperedb/office/db/_add_additionnal.py
dktorecuperedb/office/db/_add_hunfolding.py
dktorecuperedb/office/db/_get_hunfolding.py
dktorecuperedb-0.1.0b7.dist-info/LICENCE.txt
dktorecuperedb-0.1.0b7.dist-info/METADATA
dktorecuperedb-0.1.0b7.dist-info/WHEEL
dktorecuperedb-0.1.0b7.dist-info/top_level.txt
dktorecuperedb-0.1.0b7.dist-info/RECORD
