Metadata-Version: 2.1
Name: dktorecuperedb
Version: 0.1.0b7
Summary: RECUPERE databases
Home-page: https://1sixunhuit.frama.io/recupere_db
Author: Pierre
Author-email: pierre@exemple.com
License: AGPL 3
Keywords: ['profiling','profiler','line_profiler','html','report']
Classifier: Development Status :: 3 - Alpha
Classifier: Intended Audience :: Developers
Classifier: Programming Language :: Python :: 3.9
Classifier: Environment :: Console
Classifier: Operating System :: POSIX :: Linux
Classifier: Natural Language :: French
Classifier: Natural Language :: English
Classifier: License :: OSI Approved :: GNU Affero General Public License v3
Classifier: Operating System :: OS Independent
Requires-Python: >=3.9, <4
License-File: LICENCE.txt
Requires-Dist: certifi (==2022.12.7)
Requires-Dist: charset-normalizer (==3.0.1)
Requires-Dist: falcon (==2.0.0)
Requires-Dist: hug (==2.6.1)
Requires-Dist: idna (==3.4)
Requires-Dist: requests (==2.28.2)
Requires-Dist: six (==1.16.0)
Requires-Dist: urllib3 (==1.26.14)
Requires-Dist: dktoeasysqlite3 (>=0.0.1)
Requires-Dist: dktotoolkit (<=1.1.99,>=1.1.0b12)
Provides-Extra: doc
Requires-Dist: sphinx (==6.2.1) ; extra == 'doc'
Requires-Dist: sphinx-rtd-theme (==1.2.1) ; extra == 'doc'
Requires-Dist: myst-parser (==1.0.0) ; extra == 'doc'
Provides-Extra: test
Requires-Dist: coverage (==7.2.7) ; extra == 'test'
Requires-Dist: flake8 (==6.0.0) ; extra == 'test'
Requires-Dist: flake8-html (==0.4.3) ; extra == 'test'
Requires-Dist: html-report-line-profiler (>=0.1.1a) ; extra == 'test'
Provides-Extra: upload
Requires-Dist: twine (==4.0.2) ; extra == 'upload'
Requires-Dist: wheel (==0.40.0) ; extra == 'upload'
